kanripo
