Metadata-Version: 1.0
Name: kanripo
Version: 0.3
Summary: Access to the kanripo API.
Home-page: http://github.com/mandoku/kanripo
Author: Christian Wittern
Author-email: cwittern@gmail.com
License: CC by SA
Platform: UNKNOWN
